{
  "jobs": [
    {
      "job_id": "1",
      "user": "username",
      "title": "CTO",
      "description": "ACCELERATE INNOVATION",
      "employer": "META",
      "location": "SAN FRANCISCO",
      "salary": "$$$",
      "start_date": "",
      "end_date": "",
      "applications": [
        {
          "user_id": "1",
          "graduation_date": "sdfasdfas",
          "start_date": "dfasdfasdf",
          "cover_letter": "asdfasdf"
        },
        {
          "user_id": "1",
          "graduation_date": "sdfasdfa",
          "start_date": "sdfasdfasdf",
          "cover_letter": "asdfasdfasdf"
        },
        {
          "user_id": "1",
          "graduation_date": "asd",
          "start_date": "fasd",
          "cover_letter": "fas"
        },
        {
          "user_id": "1",
          "graduation_date": "s",
          "start_date": "dfas",
          "cover_letter": "dfas"
        },
        {
          "user_id": "1",
          "graduation_date": "sdf",
          "start_date": "asdf",
          "cover_letter": "asdf"
        },
        {
          "user_id": "1",
          "graduation_date": "sdafsd",
          "start_date": "fasd",
          "cover_letter": "fasdf"
        },
        {
          "user_id": "1",
          "graduation_date": "s",
          "start_date": "dfa",
          "cover_letter": "sdf"
        },
        {
          "user_id": "1",
          "graduation_date": "sdfasdfa",
          "start_date": "sdfasdf",
          "cover_letter": "asdf"
        },
        {
          "user_id": "1",
          "graduation_date": "dsafsdfasdfasdf",
          "start_date": "asdfasdf",
          "cover_letter": "asdf"
        },
        {
          "user_id": "1",
          "graduation_date": "sdfasd",
          "start_date": "fasdfasd",
          "cover_letter": "sdf"
        }
      ]
    },
    {
      "job_id": "25",
      "user": "naruto",
      "title": "best job",
      "description": "the best",
      "employer": "the best",
      "location": "the best",
      "salary": "the best",
      "start_date": "",
      "end_date": "",
      "applications": [
        {
          "user_id": "1",
          "graduation_date": "11-20-2021",
          "start_date": "11-20-2022",
          "cover_letter": "TestApplication"
        },
        {
          "user_id": "1",
          "graduation_date": "11-20-2021",
          "start_date": "11-20-2022",
          "cover_letter": "TestApplication"
        },
        {
          "user_id": "1",
          "graduation_date": "11-20-2021",
          "start_date": "11-20-2022",
          "cover_letter": "TestApplication"
        },
        {
          "user_id": "1",
          "graduation_date": "11-20-2021",
          "start_date": "11-20-2022",
          "cover_letter": "TestApplication"
        },
        {
          "user_id": "1",
          "graduation_date": "11-20-2021",
          "start_date": "11-20-2022",
          "cover_letter": "TestApplication"
        },
        {
          "user_id": "1",
          "graduation_date": "11-20-2021",
          "start_date": "11-20-2022",
          "cover_letter": "TestApplication"
        },
        {
          "user_id": "1",
          "graduation_date": "11-20-2021",
          "start_date": "11-20-2022",
          "cover_letter": "TestApplication"
        },
        {
          "user_id": "1",
          "graduation_date": "11-20-2021",
          "start_date": "11-20-2022",
          "cover_letter": "TestApplication"
        },
        {
          "user_id": "1",
          "graduation_date": "11-20-2021",
          "start_date": "11-20-2022",
          "cover_letter": "TestApplication"
        },
        {
          "user_id": "1",
          "graduation_date": "11-20-2021",
          "start_date": "11-20-2022",
          "cover_letter": "TestApplication"
        },
        {
          "user_id": "1",
          "graduation_date": "11-20-2021",
          "start_date": "11-20-2022",
          "cover_letter": "TestApplication"
        },
        {
          "user_id": "1",
          "graduation_date": "11-20-2021",
          "start_date": "11-20-2022",
          "cover_letter": "TestApplication"
        },
        {
          "user_id": "1",
          "graduation_date": "11-20-2021",
          "start_date": "11-20-2022",
          "cover_letter": "TestApplication"
        },
        {
          "user_id": "1",
          "graduation_date": "11-20-2021",
          "start_date": "11-20-2022",
          "cover_letter": "TestApplication"
        },
        {
          "user_id": "1",
          "graduation_date": "11-20-2021",
          "start_date": "11-20-2022",
          "cover_letter": "TestApplication"
        }
      ]
    },
    {
      "job_id": "26",
      "user": "naruto",
      "title": "potato",
      "description": "be a potato",
      "employer": "Mr. potato",
      "location": "potatoland",
      "salary": "1",
      "start_date": "",
      "end_date": "",
      "applications": []
    },
    {
      "job_id": "27",
      "user": "Sarutobi",
      "title": "Hokage",
      "description": "Leader of the great hidden leaf village",
      "employer": "Land of Fire",
      "location": "Hidden Leaf village",
      "salary": "100k",
      "start_date": "",
      "end_date": "",
      "applications": [
        {
          "user_id": "1",
          "graduation_date": "03/05/2023",
          "start_date": "3",
          "cover_letter": "because im so good at things"
        }
      ]
    },
    {
      "job_id": "28",
      "user": "Bilal Joud",
      "title": "Software Engineer",
      "description": "You will be a software Engineer on a scrum team with 4 other people",
      "employer": "USF",
      "location": "Tampa, FL",
      "salary": "150k",
      "start_date": "",
      "end_date": "",
      "applications": [
        {
          "user_id": "10",
          "graduation_date": "probably never",
          "start_date": "today",
          "cover_letter": "Im not a good fit, you probably shouldnt hire me."
        }
      ]
    },
    {
      "job_id": "29",
      "user": "naruto",
      "title": "h",
      "description": "This is a job Description",
      "employer": "h",
      "location": "h",
      "salary": "h",
      "start_date": "",
      "end_date": "",
      "applications": []
    }
  ]
}